cognitive/__init__.py
cognitive/algorithms/USE_soma_core_METRICS.py
cognitive/algorithms/__init__.py
cognitive/algorithms/graph_walker.py
cognitive/algorithms/nine_scorer.py
cognitive/algorithms/pattern_matcher.py
cognitive/algorithms/query_parser.py
cognitive/algorithms/semantic_similarity.py
cognitive/algorithms/soma_core_metrics.py
cognitive/algorithms/soma_ranker.py
cognitive/examples/__init__.py
cognitive/examples/numpy_gpt_integration.py
cognitive/graph/__init__.py
cognitive/graph/graph_edge.py
cognitive/graph/graph_node.py
cognitive/graph/graph_store.py
cognitive/graph/relation_extractor.py
cognitive/integration/__init__.py
cognitive/integration/cognitive_pipeline.py
cognitive/integration/embedding_bridge.py
cognitive/integration/token_bridge.py
cognitive/integration/vector_bridge.py
cognitive/memory/__init__.py
cognitive/memory/memory_object.py
cognitive/memory/unified_memory.py
cognitive/reasoning/__init__.py
cognitive/reasoning/contradiction_detector.py
cognitive/reasoning/explainer.py
cognitive/reasoning/hybrid_reasoner.py
cognitive/reasoning/inference_engine.py
cognitive/reasoning/path_finder.py
cognitive/reasoning/query_engine.py
cognitive/reasoning/rule_base.py
cognitive/reasoning/soma_reasoner.py
cognitive/reasoning/soma_verbalizer.py
cognitive/slm/__init__.py
cognitive/slm/fluency_enhancer.py
cognitive/slm/run_model.py
cognitive/slm/show_model.py
cognitive/slm/slm_constrained_decoder.py
cognitive/slm/slm_constraints.py
cognitive/slm/slm_generator.py
cognitive/slm/slm_trainer.py
cognitive/slm/small_slm.py
cognitive/slm/soma_gpt.py
cognitive/slm/soma_gpt5.py
cognitive/slm/soma_gpt_trainer.py
cognitive/slm/soma_gpt_trainer_real.py
cognitive/slm/soma_gpt_trainer_simple.py
cognitive/slm/soma_sequence_optimizer.py
cognitive/slm/soma_slm_model.py
cognitive/slm/test_small_slm.py
cognitive/slm/test_soma_model.py
cognitive/slm/tiny_slm.py
cognitive/slm/tiny_transformer.py
cognitive/slm/training_data.py
cognitive/trees/__init__.py
cognitive/trees/tree.py
somaya-1.0.5.dist-info/licenses/LICENSE
somaya-1.0.5.dist-info/METADATA
somaya-1.0.5.dist-info/WHEEL
somaya-1.0.5.dist-info/entry_points.txt
somaya-1.0.5.dist-info/top_level.txt
somaya-1.0.5.dist-info/RECORD
