Metadata-Version: 2.4
Name: somaya
Version: 1.0.5
Summary: SOMA - Advanced Tokenization & Intelligence Framework
Home-page: https://github.com/chavalasantosh/SanVerse
Author: Santosh Chavala
Author-email: Santosh Chavala <chavalasantosh@gmail.com>
License: MIT
Project-URL: Homepage, https://github.com/chavalasantosh/SanVerse
Project-URL: Documentation, https://github.com/chavalasantosh/SanVerse#readme
Project-URL: Repository, https://github.com/chavalasantosh/SanVerse.git
Project-URL: Issues, https://github.com/chavalasantosh/SanVerse/issues
Keywords: soma,tokenization,nlp,embeddings,intelligence
Classifier: Development Status :: 4 - Beta
Classifier: Intended Audience :: Developers
Classifier: Intended Audience :: Science/Research
Classifier: License :: OSI Approved :: MIT License
Classifier: Operating System :: OS Independent
Classifier: Programming Language :: Python :: 3
Classifier: Topic :: Scientific/Engineering :: Artificial Intelligence
Classifier: Topic :: Text Processing :: Linguistic
Requires-Python: >=3.8
License-File: LICENSE
Requires-Dist: requests>=2.31.0
Requires-Dist: numpy>=1.24.0
Requires-Dist: pandas>=2.0.0
Requires-Dist: fastapi>=0.104.0
Requires-Dist: uvicorn[standard]>=0.24.0
Requires-Dist: pydantic>=2.5.0
Requires-Dist: click>=8.1.7
Requires-Dist: rich>=13.7.0
Dynamic: author
Dynamic: home-page
Dynamic: license-file
Dynamic: requires-python
